<?xml version="1.0"?>
<!--
Catroid: An on-device visual programming system for Android devices
Copyright (C) 2010-2013 The Catrobat Team
(<http://developer.catrobat.org/credits>)

This program is free software: you can redistribute it and/or modify
it under the terms of the GNU Affero General Public License as
published by the Free Software Foundation, either version 3 of the
License, or (at your option) any later version.

An additional term exception under section 7 of the GNU Affero
General Public License, version 3, is available at
http://developer.catrobat.org/license_additional_term

This program is distributed in the hope that it will be useful,
but WITHOUT ANY WARRANTY; without even the implied warranty of
MERCHANTABILITY or FITNESS FOR A PARTICULAR PURPOSE. See the
GNU Affero General Public License for more details.

You should have received a copy of the GNU Affero General Public License
along with this program.  If not, see <http://www.gnu.org/licenses/>.
-->
<strings>
  <string name="registration_success">Registrierung erfolgreich!</string>
  <string name="additional_options">Andere M&#xF6;glichkeiten, um fortzufahren:</string>
  <string name="title">Einen neuen Account anlegen</string>
  <string name="nickname">Benutzername</string>
  <string name="enter_nickname">gib einen Benutzernamen ein</string>
  <string name="nickname_info">Verwende einen erfundenen Spitznamen wie (warum sollte ich nicht mit meinem richtigen Namen verwenden?).</string>
  <string name="password">Passwort</string>
  <string name="enter_password">gib ein Passwort ein</string>
  <string name="email">E-Mail Adresse</string>
  <string name="enter_email">gib deine E-Mail Adresse ein</string>
  <string name="email_info">Wir werden deinen Spitznamen, Passwort und Zugangsdaten an deine E-Mail-Adresse senden. Wir werden niemals deine E-Mail-Adresse an jemanden weitergeben. Siehe unsere {*privacyPolicyLink*} f&#xFC;r weitere Einzelheiten.</string>
  <string name="email_info_link_title">Datenschutzrichtlinien</string>
  <string name="country">Land</string>
  <string name="select_country">w&#xE4;hle dein Land aus</string>
  <string name="other">Andere</string>
  <string name="city">Stadt</string>
  <string name="enter_city">gib deine Stadt ein</string>
  <string name="birth">Geburtstag</string>
  <string name="select_month">Monat</string>
  <string name="select_year">Jahr</string>
  <string name="gender">Geschlecht</string>
  <string name="select_gender">w&#xE4;hle dein Geschlecht aus</string>
  <string name="female">weiblich</string>
  <string name="male">m&#xE4;nnlich</string>
  <string name="create">Meinen Account anlegen</string>
  <string name="login">versuch dich anzumelden, wenn du bereits ein Konto hast</string>
  <string name="password_recover">klick hier, wenn du dein Passwort vergessen hast</string>
</strings>
