<?xml version="1.0" encoding="utf-8"?>
<!--
  Catroid: An on-device visual programming system for Android devices
  Copyright (C) 2010-2014 The Catrobat Team
  (<http://developer.catrobat.org/credits>)
  
  This program is free software: you can redistribute it and/or modify
  it under the terms of the GNU Affero General Public License as
  published by the Free Software Foundation, either version 3 of the
  License, or (at your option) any later version.
  
  An additional term exception under section 7 of the GNU Affero
  General Public License, version 3, is available at
  http://developer.catrobat.org/license_additional_term
  
  This program is distributed in the hope that it will be useful,
  but WITHOUT ANY WARRANTY; without even the implied warranty of
  MERCHANTABILITY or FITNESS FOR A PARTICULAR PURPOSE. See the
  GNU Affero General Public License for more details.
  
  You should have received a copy of the GNU Affero General Public License
  along with this program. If not, see <http://www.gnu.org/licenses/>.
-->
<strings>
  <string name="title">Registrierung erfolgreich!</string>
  <string name="nickname">Einloggen</string>
  <string name="enter_nickname">gib deine E-Mail Adresse ein</string>
  <string name="nickname_info">m&#xE4;nnlich</string>
  <string name="password">Einloggen</string>
  <string name="enter_password">Username</string>
  <string name="email">E-Mail-Adresse</string>
  <string name="enter_email">Datenschutzrichtlinien</string>
  <string name="email_info">Andere</string>
  <string name="email_info_link_title">Monat</string>
  <string name="country">Du hast deinen Avatar erfolgreich ge&#xE4;ndert.</string>
  <string name="select_country">Passwort eingeben</string>
  <string name="other">Die neue E-Mail-Adresse wurde erfolgreich hinzugef&#xFC;gt. Bitte &#xFC;berpr&#xFC;fen Sie Ihren Posteingang um dies zu &#xFC;berpr&#xFC;fen.</string>
  <string name="city">w&#xE4;hle dein Land aus</string>
  <string name="enter_city">Stadt</string>
  <string name="birth">gib deine Stadt ein</string>
  <string name="select_month">Jahr</string>
  <string name="select_year">&gt;w&#xE4;hle dein Geschlecht aus</string>
  <string name="gender">weiblich</string>
  <string name="select_gender">Meinen Account anlegen</string>
  <string name="female">versuch dich anzumelden, wenn du bereits ein Konto hast</string>
  <string name="male">Geben Sie einen neuen Nicknamen ein</string>
  <string name="create">Passwort</string>
  <string name="login">Geburtstag</string>
  <string name="password_recover">Geschlecht</string>
  <string name="additional_options">Passwort</string>
  <string name="registration_success">Registrierung erfolgreich!</string>
</strings>
